{
  "data": {
    "merlin": {
      "__typename": "MerlinQuery",
      "pdpPhotoTour": {
        "__typename": "MerlinPdpPhotoTourResponse",
        "roomsOverviewTitle": null,
        "images": [
          {
            "__typename": "MerlinImage",
            "id": "1200954347",
            "baseUrl": "https://a0.muscache.com/im/pictures/miso/Hosting-15468867/original/90bf6244-e9b6-4310-83b7-5448aff8c5ee.jpeg",
            "previewEncodedPng": "",
            "accessibilityLabel": "Living Room",
            "displayAspectRatio": null,
            "orientation": "LANDSCAPE",
            "imageMetadata": {
              "__typename": "MerlinImageMetadata",
              "caption": "Living Room",
              "imageType": "COVER",
              "isProfessional": false
            }
          },
          {
            "__typename": "MerlinImage",
            "id": "1200954659",
            "baseUrl": "https://a0.muscache.com/im/pictures/miso/Hosting-15468867/original/4183f8ec-0288-4afa-aca3-1e38eb2ba89d.jpeg",
            "previewEncodedPng": "",
            "accessibilityLabel": "Bedroom",
            "displayAspectRatio": null,
            "orientation": "LANDSCAPE",
            "imageMetadata": {
              "__typename": "MerlinImageMetadata",
              "caption": "Bedroom",
              "imageType": "DETAIL",
              "isProfessional": false
            }
          },
          {
            "__typename": "MerlinImage",
            "id": "1200955140",
            "baseUrl": "https://a0.muscache.com/im/pictures/miso/Hosting-15468867/original/0a04d087-d6ce-461b-bec4-e36377d5bf9a.jpeg",
            "previewEncodedPng": "",
            "accessibilityLabel": "Bedroom looking into living room and kitchen",
            "displayAspectRatio": null,
            "orientation": "LANDSCAPE",
            "imageMetadata": {
              "__typename": "MerlinImageMetadata",
              "caption": "Bedroom looking into living room and kitchen",
              "imageType": "DETAIL",
              "isProfessional": false
            }
          },
          {
            "__typename": "MerlinImage",
            "id": "1784437063",
            "baseUrl": "https://a0.muscache.com/im/pictures/ab1afb4a-8f18-4ec9-8599-1dadb7004ac0.jpg",
            "previewEncodedPng": "",
            "accessibilityLabel": "Listing image 4",
            "displayAspectRatio": null,
            "orientation": "LANDSCAPE",
            "imageMetadata": {
              "__typename": "MerlinImageMetadata",
              "caption": "",
              "imageType": "DETAIL",
              "isProfessional": false
            }
          },
          {
            "__typename": "MerlinImage",
            "id": "1784437184",
            "baseUrl": "https://a0.muscache.com/im/pictures/5974e906-ffaf-440e-a59d-4773d1b0c9d3.jpg",
            "previewEncodedPng": "",
            "accessibilityLabel": "Listing image 5",
            "displayAspectRatio": null,
            "orientation": "LANDSCAPE",
            "imageMetadata": {
              "__typename": "MerlinImageMetadata",
              "caption": "",
              "imageType": "DETAIL",
              "isProfessional": false
            }
          },
          {
            "__typename": "MerlinImage",
            "id": "1200955455",
            "baseUrl": "https://a0.muscache.com/im/pictures/miso/Hosting-15468867/original/bf275c57-a0ef-423d-9cf6-4a815cc1d5e3.jpeg",
            "previewEncodedPng": "",
            "accessibilityLabel": "Bathroom",
            "displayAspectRatio": null,
            "orientation": "LANDSCAPE",
            "imageMetadata": {
              "__typename": "MerlinImageMetadata",
              "caption": "Bathroom",
              "imageType": "DETAIL",
              "isProfessional": false
            }
          },
          {
            "__typename": "MerlinImage",
            "id": "1200956279",
            "baseUrl": "https://a0.muscache.com/im/pictures/miso/Hosting-15468867/original/a7ede5ec-0d66-45e9-8226-22adbc7323af.jpeg",
            "previewEncodedPng": "",
            "accessibilityLabel": "Private courtyard",
            "displayAspectRatio": null,
            "orientation": "LANDSCAPE",
            "imageMetadata": {
              "__typename": "MerlinImageMetadata",
              "caption": "Private courtyard",
              "imageType": "DETAIL",
              "isProfessional": false
            }
          },
          {
            "__typename": "MerlinImage",
            "id": "1784434430",
            "baseUrl": "https://a0.muscache.com/im/pictures/8ed23254-b225-4419-853f-fc734d23ba76.jpg",
            "previewEncodedPng": "",
            "accessibilityLabel": "Lassing Park a block away",
            "displayAspectRatio": null,
            "orientation": "LANDSCAPE",
            "imageMetadata": {
              "__typename": "MerlinImageMetadata",
              "caption": "Lassing Park a block away",
              "imageType": "DETAIL",
              "isProfessional": false
            }
          },
          {
            "__typename": "MerlinImage",
            "id": "1200958433",
            "baseUrl": "https://a0.muscache.com/im/pictures/miso/Hosting-15468867/original/e9f1adb5-1819-46a4-a6cc-0a2b23dcfbc3.jpeg",
            "previewEncodedPng": "",
            "accessibilityLabel": "Aerial location",
            "displayAspectRatio": null,
            "orientation": "LANDSCAPE",
            "imageMetadata": {
              "__typename": "MerlinImageMetadata",
              "caption": "Aerial location",
              "imageType": "DETAIL",
              "isProfessional": false
            }
          },
          {
            "__typename": "MerlinImage",
            "id": "1200974675",
            "baseUrl": "https://a0.muscache.com/im/pictures/miso/Hosting-15468867/original/85c2bacd-73e0-43ac-860a-d3ec6c916f90.jpeg",
            "previewEncodedPng": "",
            "accessibilityLabel": "Lassing Park at the end of the street.",
            "displayAspectRatio": null,
            "orientation": "LANDSCAPE",
            "imageMetadata": {
              "__typename": "MerlinImageMetadata",
              "caption": "Lassing Park at the end of the street.",
              "imageType": "DETAIL",
              "isProfessional": false
            }
          }
        ],
        "roomTourLayoutInfos": [
          {
            "__typename": "MerlinRoomTourLayoutInfo",
            "roomTourItems": [
              {
                "__typename": "MerlinRoomTourItem",
                "title": null,
                "highlights": null,
                "imageIds": [
                  "1200954347",
                  "1200954659",
                  "1200955140",
                  "1784437063",
                  "1784437184",
                  "1200955455",
                  "1200956279",
                  "1784434430",
                  "1200958433",
                  "1200974675"
                ],
                "mediaBlocks": [
                  {
                    "__typename": "MerlinMediaBlockContainer",
                    "flip": "DEFAULT",
                    "format": "ONE_LANDSCAPE",
                    "mediaBlock": {
                      "__typename": "MerlinOneLandscapeMediaBlock",
                      "landscapeId": "1200954347"
                    }
                  },
                  {
                    "__typename": "MerlinMediaBlockContainer",
                    "flip": "DEFAULT",
                    "format": "TWO_LANDSCAPES",
                    "mediaBlock": {
                      "__typename": "MerlinTwoLandscapesMediaBlock",
                      "leftLandscapeId": "1200954659",
                      "rightLandscapeId": "1200955140"
                    }
                  },
                  {
                    "__typename": "MerlinMediaBlockContainer",
                    "flip": "DEFAULT",
                    "format": "ONE_LANDSCAPE",
                    "mediaBlock": {
                      "__typename": "MerlinOneLandscapeMediaBlock",
                      "landscapeId": "1784437063"
                    }
                  },
                  {
                    "__typename": "MerlinMediaBlockContainer",
                    "flip": "DEFAULT",
                    "format": "TWO_LANDSCAPES",
                    "mediaBlock": {
                      "__typename": "MerlinTwoLandscapesMediaBlock",
                      "leftLandscapeId": "1784437184",
                      "rightLandscapeId": "1200955455"
                    }
                  },
                  {
                    "__typename": "MerlinMediaBlockContainer",
                    "flip": "DEFAULT",
                    "format": "ONE_LANDSCAPE",
                    "mediaBlock": {
                      "__typename": "MerlinOneLandscapeMediaBlock",
                      "landscapeId": "1200956279"
                    }
                  },
                  {
                    "__typename": "MerlinMediaBlockContainer",
                    "flip": "DEFAULT",
                    "format": "TWO_LANDSCAPES",
                    "mediaBlock": {
                      "__typename": "MerlinTwoLandscapesMediaBlock",
                      "leftLandscapeId": "1784434430",
                      "rightLandscapeId": "1200958433"
                    }
                  },
                  {
                    "__typename": "MerlinMediaBlockContainer",
                    "flip": "DEFAULT",
                    "format": "ONE_LANDSCAPE",
                    "mediaBlock": {
                      "__typename": "MerlinOneLandscapeMediaBlock",
                      "landscapeId": "1200974675"
                    }
                  }
                ]
              }
            ]
          }
        ],
        "gridImageLoggingEventData": {
          "__typename": "MerlinLoggingEventData",
          "loggingId": "pdp.photoTour.gridImage",
          "section": "photoTour",
          "component": "gridImage",
          "experiments": null
        },
        "carouselImageNavigationLoggingEventData": {
          "__typename": "MerlinLoggingEventData",
          "loggingId": "pdp.photoTour.carouselImageNavigation",
          "section": "photoTour",
          "component": "carouselImageNavigation",
          "experiments": null
        },
        "saveButton": {
          "__typename": "MerlinBasicListItem",
          "title": "Save",
          "subtitle": null,
          "loggingEventData": {
            "__typename": "MerlinLoggingEventData",
            "loggingId": "pdp.photoTour.save",
            "section": "photoTour",
            "component": "save",
            "experiments": null
          }
        },
        "unsaveButton": {
          "__typename": "MerlinBasicListItem",
          "title": "Saved",
          "subtitle": null,
          "loggingEventData": {
            "__typename": "MerlinLoggingEventData",
            "loggingId": "pdp.photoTour.unsave",
            "section": "photoTour",
            "component": "unsave",
            "experiments": null
          }
        },
        "shareButton": {
          "__typename": "MerlinBasicListItem",
          "title": "Share",
          "subtitle": null,
          "loggingEventData": {
            "__typename": "MerlinLoggingEventData",
            "loggingId": "pdp.photoTour.share",
            "section": "photoTour",
            "component": "share",
            "experiments": null
          }
        },
        "closeButton": {
          "__typename": "MerlinBasicListItem",
          "title": "Close",
          "anchor": null,
          "icon": null,
          "loggingEventData": {
            "__typename": "MerlinLoggingEventData",
            "component": "close",
            "section": "photoTour",
            "loggingId": "pdp.photoTour.close"
          }
        },
        "seePhotosButton": {
          "__typename": "MerlinBasicListItem",
          "title": "Show all photos",
          "loggingEventData": {
            "__typename": "MerlinLoggingEventData",
            "loggingId": "pdp.photoTour.seePhotos",
            "section": "photoTour",
            "component": "seePhotos",
            "experiments": null
          }
        }
      }
    }
  },
  "extensions": {
    "traceId": "k0X_cdVeoZXItkrLBfOx2w=="
  }
}